jpb/__init__.py
jpb/jpb.py
JPB-0.0.1.dist-info/LICENSE
JPB-0.0.1.dist-info/METADATA
JPB-0.0.1.dist-info/WHEEL
JPB-0.0.1.dist-info/top_level.txt
JPB-0.0.1.dist-info/RECORD
