Metadata-Version: 2.1
Name: JPB
Version: 0.0.1
Summary: Automatization Bot For Jackbox Party Pack Games
Author: Loamf
Author-email: <loamf2@gmail.com>
Keywords: python,jackbox,automatization,jackbox24
Classifier: Development Status :: 1 - Planning
Classifier: Intended Audience :: Developers
Classifier: Programming Language :: Python :: 3
Classifier: Operating System :: Microsoft :: Windows
License-File: LICENSE
Requires-Dist: opencv-python
Requires-Dist: pyautogui
Requires-Dist: datetime
Requires-Dist: numpy
